[{"secureConnectionStart": 0, "redirectStart": 0, "domContentLoadedEventStart": 1498557873855, "redirectEnd": 0, "loadEventStart": 1498557874071, "unloadEventStart": 0, "domainLookupEnd": 1498557873399, "connectEnd": 1498557873399, "unloadEventEnd": 0, "requestStart": 1498557873429, "responseEnd": 1498557873537, "navigationStart": 1498557873392, "domLoading": 1498557873538, "loadEventEnd": 1498557874072, "domInteractive": 1498557873855, "fetchStart": 1498557873399, "responseStart": 1498557873526, "domContentLoadedEventEnd": 1498557873860, "domComplete": 1498557874067, "connectStart": 1498557873399, "domainLookupStart": 1498557873399}, {"secureConnectionStart": 0, "redirectStart": 0, "domContentLoadedEventStart": 1498557870709, "redirectEnd": 0, "loadEventStart": 1498557870982, "unloadEventStart": 0, "domainLookupEnd": 1498557870072, "connectEnd": 1498557870072, "unloadEventEnd": 0, "requestStart": 1498557870096, "responseEnd": 1498557870186, "navigationStart": 1498557870066, "domLoading": 1498557870185, "loadEventEnd": 1498557870985, "domInteractive": 1498557870709, "fetchStart": 1498557870072, "responseStart": 1498557870173, "domContentLoadedEventEnd": 1498557870715, "domComplete": 1498557870974, "connectStart": 1498557870072, "domainLookupStart": 1498557870072}, {"secureConnectionStart": 0, "redirectStart": 0, "domContentLoadedEventStart": 1498557866169, "redirectEnd": 0, "loadEventStart": 1498557866381, "unloadEventStart": 0, "domainLookupEnd": 1498557865750, "connectEnd": 1498557865750, "unloadEventEnd": 0, "requestStart": 1498557865775, "responseEnd": 1498557865873, "navigationStart": 1498557865743, "domLoading": 1498557865875, "loadEventEnd": 1498557866383, "domInteractive": 1498557866169, "fetchStart": 1498557865750, "responseStart": 1498557865860, "domContentLoadedEventEnd": 1498557866173, "domComplete": 1498557866379, "connectStart": 1498557865750, "domainLookupStart": 1498557865750}, {"secureConnectionStart": 0, "redirectStart": 0, "domContentLoadedEventStart": 1498557862592, "redirectEnd": 0, "loadEventStart": 1498557862871, "unloadEventStart": 0, "domainLookupEnd": 1498557862026, "connectEnd": 1498557862026, "unloadEventEnd": 0, "requestStart": 1498557862076, "responseEnd": 1498557862347, "navigationStart": 1498557862019, "domLoading": 1498557862302, "loadEventEnd": 1498557862871, "domInteractive": 1498557862592, "fetchStart": 1498557862026, "responseStart": 1498557862290, "domContentLoadedEventEnd": 1498557862594, "domComplete": 1498557862867, "connectStart": 1498557862026, "domainLookupStart": 1498557862026}, {"secureConnectionStart": 0, "redirectStart": 0, "domContentLoadedEventStart": 1498557858448, "redirectEnd": 0, "loadEventStart": 1498557858663, "unloadEventStart": 0, "domainLookupEnd": 1498557858033, "connectEnd": 1498557858033, "unloadEventEnd": 0, "requestStart": 1498557858064, "responseEnd": 1498557858149, "navigationStart": 1498557858027, "domLoading": 1498557858147, "loadEventEnd": 1498557858665, "domInteractive": 1498557858448, "fetchStart": 1498557858033, "responseStart": 1498557858137, "domContentLoadedEventEnd": 1498557858458, "domComplete": 1498557858661, "connectStart": 1498557858033, "domainLookupStart": 1498557858033}, {"secureConnectionStart": 0, "redirectStart": 0, "domContentLoadedEventStart": 1498557854390, "redirectEnd": 0, "loadEventStart": 1498557854576, "unloadEventStart": 0, "domainLookupEnd": 1498557853845, "connectEnd": 1498557853845, "unloadEventEnd": 0, "requestStart": 1498557853879, "responseEnd": 1498557854053, "navigationStart": 1498557853839, "domLoading": 1498557854050, "loadEventEnd": 1498557854577, "domInteractive": 1498557854390, "fetchStart": 1498557853845, "responseStart": 1498557854039, "domContentLoadedEventEnd": 1498557854393, "domComplete": 1498557854574, "connectStart": 1498557853845, "domainLookupStart": 1498557853845}, {"secureConnectionStart": 0, "redirectStart": 0, "domContentLoadedEventStart": 1498557849200, "redirectEnd": 0, "loadEventStart": 1498557849490, "unloadEventStart": 0, "domainLookupEnd": 1498557848522, "connectEnd": 1498557848522, "unloadEventEnd": 0, "requestStart": 1498557848548, "responseEnd": 1498557848699, "navigationStart": 1498557848515, "domLoading": 1498557848686, "loadEventEnd": 1498557849493, "domInteractive": 1498557849200, "fetchStart": 1498557848522, "responseStart": 1498557848671, "domContentLoadedEventEnd": 1498557849205, "domComplete": 1498557849485, "connectStart": 1498557848522, "domainLookupStart": 1498557848522}, {"secureConnectionStart": 0, "redirectStart": 0, "domContentLoadedEventStart": 1498557845251, "redirectEnd": 0, "loadEventStart": 1498557845492, "unloadEventStart": 0, "domainLookupEnd": 1498557844680, "connectEnd": 1498557844680, "unloadEventEnd": 0, "requestStart": 1498557844706, "responseEnd": 1498557844975, "navigationStart": 1498557844674, "domLoading": 1498557844973, "loadEventEnd": 1498557845493, "domInteractive": 1498557845251, "fetchStart": 1498557844680, "responseStart": 1498557844961, "domContentLoadedEventEnd": 1498557845257, "domComplete": 1498557845486, "connectStart": 1498557844680, "domainLookupStart": 1498557844680}, {"secureConnectionStart": 0, "redirectStart": 0, "domContentLoadedEventStart": 1498557840943, "redirectEnd": 0, "loadEventStart": 1498557841146, "unloadEventStart": 0, "domainLookupEnd": 1498557840505, "connectEnd": 1498557840505, "unloadEventEnd": 0, "requestStart": 1498557840530, "responseEnd": 1498557840630, "navigationStart": 1498557840500, "domLoading": 1498557840632, "loadEventEnd": 1498557841148, "domInteractive": 1498557840943, "fetchStart": 1498557840505, "responseStart": 1498557840614, "domContentLoadedEventEnd": 1498557840947, "domComplete": 1498557841144, "connectStart": 1498557840505, "domainLookupStart": 1498557840505}, {"secureConnectionStart": 0, "redirectStart": 0, "domContentLoadedEventStart": 1498557837670, "redirectEnd": 0, "loadEventStart": 1498557837930, "unloadEventStart": 0, "domainLookupEnd": 1498557836904, "connectEnd": 1498557836987, "unloadEventEnd": 0, "requestStart": 1498557836989, "responseEnd": 1498557837138, "navigationStart": 1498557836892, "domLoading": 1498557837139, "loadEventEnd": 1498557837934, "domInteractive": 1498557837670, "fetchStart": 1498557836904, "responseStart": 1498557837125, "domContentLoadedEventEnd": 1498557837675, "domComplete": 1498557837925, "connectStart": 1498557836944, "domainLookupStart": 1498557836904}, {"secureConnectionStart": 0, "redirectStart": 0, "domContentLoadedEventStart": 1498557486102, "redirectEnd": 0, "loadEventStart": 1498557486164, "unloadEventStart": 0, "domainLookupEnd": 1498557485955, "connectEnd": 1498557485961, "unloadEventEnd": 0, "requestStart": 1498557485961, "responseEnd": 1498557486042, "navigationStart": 1498557485952, "domLoading": 1498557486029, "loadEventEnd": 1498557486164, "domInteractive": 1498557486102, "fetchStart": 1498557485952, "responseStart": 1498557486020, "domContentLoadedEventEnd": 1498557486103, "domComplete": 1498557486163, "connectStart": 1498557485955, "domainLookupStart": 1498557485954}, {"secureConnectionStart": 0, "redirectStart": 0, "domContentLoadedEventStart": 1498557398644, "redirectEnd": 0, "loadEventStart": 1498557398710, "unloadEventStart": 0, "domainLookupEnd": 1498557398470, "connectEnd": 1498557398478, "unloadEventEnd": 0, "requestStart": 1498557398479, "responseEnd": 1498557398569, "navigationStart": 1498557398458, "domLoading": 1498557398556, "loadEventEnd": 1498557398710, "domInteractive": 1498557398644, "fetchStart": 1498557398458, "responseStart": 1498557398541, "domContentLoadedEventEnd": 1498557398645, "domComplete": 1498557398710, "connectStart": 1498557398471, "domainLookupStart": 1498557398459}, {"secureConnectionStart": 0, "redirectStart": 0, "domContentLoadedEventStart": 1498557381747, "redirectEnd": 0, "loadEventStart": 1498557381972, "unloadEventStart": 0, "domainLookupEnd": 1498557381308, "connectEnd": 1498557381308, "unloadEventEnd": 0, "requestStart": 1498557381335, "responseEnd": 1498557381433, "navigationStart": 1498557381302, "domLoading": 1498557381434, "loadEventEnd": 1498557381973, "domInteractive": 1498557381747, "fetchStart": 1498557381308, "responseStart": 1498557381411, "domContentLoadedEventEnd": 1498557381752, "domComplete": 1498557381966, "connectStart": 1498557381308, "domainLookupStart": 1498557381308}, {"secureConnectionStart": 0, "redirectStart": 0, "domContentLoadedEventStart": 1498557378611, "redirectEnd": 0, "loadEventStart": 1498557378835, "unloadEventStart": 0, "domainLookupEnd": 1498557378052, "connectEnd": 1498557378052, "unloadEventEnd": 0, "requestStart": 1498557378081, "responseEnd": 1498557378323, "navigationStart": 1498557378045, "domLoading": 1498557378275, "loadEventEnd": 1498557378838, "domInteractive": 1498557378610, "fetchStart": 1498557378052, "responseStart": 1498557378254, "domContentLoadedEventEnd": 1498557378614, "domComplete": 1498557378832, "connectStart": 1498557378052, "domainLookupStart": 1498557378052}, {"secureConnectionStart": 0, "redirectStart": 0, "domContentLoadedEventStart": 1498557373466, "redirectEnd": 0, "loadEventStart": 1498557373929, "unloadEventStart": 0, "domainLookupEnd": 1498557373043, "connectEnd": 1498557373043, "unloadEventEnd": 0, "requestStart": 1498557373069, "responseEnd": 1498557373182, "navigationStart": 1498557373037, "domLoading": 1498557373160, "loadEventEnd": 1498557373931, "domInteractive": 1498557373466, "fetchStart": 1498557373043, "responseStart": 1498557373150, "domContentLoadedEventEnd": 1498557373471, "domComplete": 1498557373926, "connectStart": 1498557373043, "domainLookupStart": 1498557373043}, {"secureConnectionStart": 0, "redirectStart": 0, "domContentLoadedEventStart": 1498557368378, "redirectEnd": 0, "loadEventStart": 1498557368565, "unloadEventStart": 0, "domainLookupEnd": 1498557367955, "connectEnd": 1498557367955, "unloadEventEnd": 0, "requestStart": 1498557367980, "responseEnd": 1498557368064, "navigationStart": 1498557367949, "domLoading": 1498557368066, "loadEventEnd": 1498557368566, "domInteractive": 1498557368378, "fetchStart": 1498557367955, "responseStart": 1498557368057, "domContentLoadedEventEnd": 1498557368383, "domComplete": 1498557368562, "connectStart": 1498557367955, "domainLookupStart": 1498557367955}, {"secureConnectionStart": 0, "redirectStart": 0, "domContentLoadedEventStart": 1498557365064, "redirectEnd": 0, "loadEventStart": 1498557365353, "unloadEventStart": 0, "domainLookupEnd": 1498557364394, "connectEnd": 1498557364394, "unloadEventEnd": 0, "requestStart": 1498557364431, "responseEnd": 1498557364537, "navigationStart": 1498557364384, "domLoading": 1498557364538, "loadEventEnd": 1498557365357, "domInteractive": 1498557365064, "fetchStart": 1498557364394, "responseStart": 1498557364519, "domContentLoadedEventEnd": 1498557365069, "domComplete": 1498557365346, "connectStart": 1498557364394, "domainLookupStart": 1498557364394}, {"secureConnectionStart": 0, "redirectStart": 0, "domContentLoadedEventStart": 1498557359111, "redirectEnd": 0, "loadEventStart": 1498557359327, "unloadEventStart": 0, "domainLookupEnd": 1498557358495, "connectEnd": 1498557358495, "unloadEventEnd": 0, "requestStart": 1498557358525, "responseEnd": 1498557358800, "navigationStart": 1498557358488, "domLoading": 1498557358801, "loadEventEnd": 1498557359328, "domInteractive": 1498557359111, "fetchStart": 1498557358495, "responseStart": 1498557358788, "domContentLoadedEventEnd": 1498557359118, "domComplete": 1498557359324, "connectStart": 1498557358495, "domainLookupStart": 1498557358495}, {"secureConnectionStart": 0, "redirectStart": 0, "domContentLoadedEventStart": 1498557354935, "redirectEnd": 0, "loadEventStart": 1498557355140, "unloadEventStart": 0, "domainLookupEnd": 1498557354502, "connectEnd": 1498557354502, "unloadEventEnd": 0, "requestStart": 1498557354529, "responseEnd": 1498557354610, "navigationStart": 1498557354496, "domLoading": 1498557354612, "loadEventEnd": 1498557355142, "domInteractive": 1498557354935, "fetchStart": 1498557354502, "responseStart": 1498557354603, "domContentLoadedEventEnd": 1498557354938, "domComplete": 1498557355137, "connectStart": 1498557354502, "domainLookupStart": 1498557354502}, {"secureConnectionStart": 0, "redirectStart": 0, "domContentLoadedEventStart": 1498557351718, "redirectEnd": 0, "loadEventStart": 1498557351890, "unloadEventStart": 0, "domainLookupEnd": 1498557350796, "connectEnd": 1498557350796, "unloadEventEnd": 0, "requestStart": 1498557350825, "responseEnd": 1498557351019, "navigationStart": 1498557350789, "domLoading": 1498557351021, "loadEventEnd": 1498557351891, "domInteractive": 1498557351718, "fetchStart": 1498557350796, "responseStart": 1498557351014, "domContentLoadedEventEnd": 1498557351724, "domComplete": 1498557351888, "connectStart": 1498557350796, "domainLookupStart": 1498557350796}]
